README.md
setup.py
m6anet/__init__.py
m6anet/model/__init__.py
m6anet/model/model.py
m6anet/model/configs/model_configs/prod_pooling.toml
m6anet/model/model_blocks/__init__.py
m6anet/model/model_blocks/blocks.py
m6anet/model/model_blocks/pooling_blocks.py
m6anet/model/model_states/prod_pooling_pr_auc.pt
m6anet/model/norm_factors/norm_dict.joblib
m6anet/scripts/__init__.py
m6anet/scripts/compute_normalization_factors.py
m6anet/scripts/constants.py
m6anet/scripts/cross_validate.py
m6anet/scripts/dataprep.py
m6anet/scripts/helper.py
m6anet/scripts/run_inference.py
m6anet/scripts/train.py
m6anet/utils/__init__.py
m6anet/utils/builder.py
m6anet/utils/data_utils.py
m6anet/utils/inference_utils.py
m6anet/utils/misc.py
m6anet/utils/sampler_utils.py
m6anet/utils/training_utils.py
m6anet/utils/loss_functions/__init__.py
m6anet/utils/loss_functions/loss_functions.py
m6anet_gh_action.egg-info/PKG-INFO
m6anet_gh_action.egg-info/SOURCES.txt
m6anet_gh_action.egg-info/dependency_links.txt
m6anet_gh_action.egg-info/entry_points.txt
m6anet_gh_action.egg-info/requires.txt
m6anet_gh_action.egg-info/top_level.txt